{
    "parent": "block/copper_block",
    "overrides": [
		{ "predicate": { "custom_model_data": 6421000 }, "model": "mechanization:machines/liquid_pipe/pipe" },
		{ "predicate": { "custom_model_data": 6421001 }, "model": "mechanization:machines/liquid_pipe/pipe_u" },
		{ "predicate": { "custom_model_data": 6421002 }, "model": "mechanization:machines/liquid_pipe/pipe_d" },
		{ "predicate": { "custom_model_data": 6421003 }, "model": "mechanization:machines/liquid_pipe/pipe_ud" },
		{ "predicate": { "custom_model_data": 6421004 }, "model": "mechanization:machines/liquid_pipe/pipe_n" },
		{ "predicate": { "custom_model_data": 6421005 }, "model": "mechanization:machines/liquid_pipe/pipe_un" },
		{ "predicate": { "custom_model_data": 6421006 }, "model": "mechanization:machines/liquid_pipe/pipe_dn" },
		{ "predicate": { "custom_model_data": 6421007 }, "model": "mechanization:machines/liquid_pipe/pipe_udn" },
		{ "predicate": { "custom_model_data": 6421008 }, "model": "mechanization:machines/liquid_pipe/pipe_s" },
		{ "predicate": { "custom_model_data": 6421009 }, "model": "mechanization:machines/liquid_pipe/pipe_us" },
		{ "predicate": { "custom_model_data": 6421010 }, "model": "mechanization:machines/liquid_pipe/pipe_ds" },
		{ "predicate": { "custom_model_data": 6421011 }, "model": "mechanization:machines/liquid_pipe/pipe_uds" },
		{ "predicate": { "custom_model_data": 6421012 }, "model": "mechanization:machines/liquid_pipe/pipe_ns" },
		{ "predicate": { "custom_model_data": 6421013 }, "model": "mechanization:machines/liquid_pipe/pipe_uns" },
		{ "predicate": { "custom_model_data": 6421014 }, "model": "mechanization:machines/liquid_pipe/pipe_dns" },
		{ "predicate": { "custom_model_data": 6421015 }, "model": "mechanization:machines/liquid_pipe/pipe_udns" },
		{ "predicate": { "custom_model_data": 6421016 }, "model": "mechanization:machines/liquid_pipe/pipe_e" },
		{ "predicate": { "custom_model_data": 6421017 }, "model": "mechanization:machines/liquid_pipe/pipe_ue" },
		{ "predicate": { "custom_model_data": 6421018 }, "model": "mechanization:machines/liquid_pipe/pipe_de" },
		{ "predicate": { "custom_model_data": 6421019 }, "model": "mechanization:machines/liquid_pipe/pipe_ude" },
		{ "predicate": { "custom_model_data": 6421020 }, "model": "mechanization:machines/liquid_pipe/pipe_ne" },
		{ "predicate": { "custom_model_data": 6421021 }, "model": "mechanization:machines/liquid_pipe/pipe_une" },
		{ "predicate": { "custom_model_data": 6421022 }, "model": "mechanization:machines/liquid_pipe/pipe_dne" },
		{ "predicate": { "custom_model_data": 6421023 }, "model": "mechanization:machines/liquid_pipe/pipe_udne" },
		{ "predicate": { "custom_model_data": 6421024 }, "model": "mechanization:machines/liquid_pipe/pipe_se" },
		{ "predicate": { "custom_model_data": 6421025 }, "model": "mechanization:machines/liquid_pipe/pipe_use" },
		{ "predicate": { "custom_model_data": 6421026 }, "model": "mechanization:machines/liquid_pipe/pipe_dse" },
		{ "predicate": { "custom_model_data": 6421027 }, "model": "mechanization:machines/liquid_pipe/pipe_udse" },
		{ "predicate": { "custom_model_data": 6421028 }, "model": "mechanization:machines/liquid_pipe/pipe_nse" },
		{ "predicate": { "custom_model_data": 6421029 }, "model": "mechanization:machines/liquid_pipe/pipe_unse" },
		{ "predicate": { "custom_model_data": 6421030 }, "model": "mechanization:machines/liquid_pipe/pipe_dnse" },
		{ "predicate": { "custom_model_data": 6421031 }, "model": "mechanization:machines/liquid_pipe/pipe_udnse" },
		{ "predicate": { "custom_model_data": 6421032 }, "model": "mechanization:machines/liquid_pipe/pipe_w" },
		{ "predicate": { "custom_model_data": 6421033 }, "model": "mechanization:machines/liquid_pipe/pipe_uw" },
		{ "predicate": { "custom_model_data": 6421034 }, "model": "mechanization:machines/liquid_pipe/pipe_dw" },
		{ "predicate": { "custom_model_data": 6421035 }, "model": "mechanization:machines/liquid_pipe/pipe_udw" },
		{ "predicate": { "custom_model_data": 6421036 }, "model": "mechanization:machines/liquid_pipe/pipe_nw" },
		{ "predicate": { "custom_model_data": 6421037 }, "model": "mechanization:machines/liquid_pipe/pipe_unw" },
		{ "predicate": { "custom_model_data": 6421038 }, "model": "mechanization:machines/liquid_pipe/pipe_dnw" },
		{ "predicate": { "custom_model_data": 6421039 }, "model": "mechanization:machines/liquid_pipe/pipe_udnw" },
		{ "predicate": { "custom_model_data": 6421040 }, "model": "mechanization:machines/liquid_pipe/pipe_sw" },
		{ "predicate": { "custom_model_data": 6421041 }, "model": "mechanization:machines/liquid_pipe/pipe_usw" },
		{ "predicate": { "custom_model_data": 6421042 }, "model": "mechanization:machines/liquid_pipe/pipe_dsw" },
		{ "predicate": { "custom_model_data": 6421043 }, "model": "mechanization:machines/liquid_pipe/pipe_udsw" },
		{ "predicate": { "custom_model_data": 6421044 }, "model": "mechanization:machines/liquid_pipe/pipe_nsw" },
		{ "predicate": { "custom_model_data": 6421045 }, "model": "mechanization:machines/liquid_pipe/pipe_unsw" },
		{ "predicate": { "custom_model_data": 6421046 }, "model": "mechanization:machines/liquid_pipe/pipe_dnsw" },
		{ "predicate": { "custom_model_data": 6421047 }, "model": "mechanization:machines/liquid_pipe/pipe_udnsw" },
		{ "predicate": { "custom_model_data": 6421048 }, "model": "mechanization:machines/liquid_pipe/pipe_ew" },
		{ "predicate": { "custom_model_data": 6421049 }, "model": "mechanization:machines/liquid_pipe/pipe_uew" },
		{ "predicate": { "custom_model_data": 6421050 }, "model": "mechanization:machines/liquid_pipe/pipe_dew" },
		{ "predicate": { "custom_model_data": 6421051 }, "model": "mechanization:machines/liquid_pipe/pipe_udew" },
		{ "predicate": { "custom_model_data": 6421052 }, "model": "mechanization:machines/liquid_pipe/pipe_new" },
		{ "predicate": { "custom_model_data": 6421053 }, "model": "mechanization:machines/liquid_pipe/pipe_unew" },
		{ "predicate": { "custom_model_data": 6421054 }, "model": "mechanization:machines/liquid_pipe/pipe_dnew" },
		{ "predicate": { "custom_model_data": 6421055 }, "model": "mechanization:machines/liquid_pipe/pipe_udnew" },
		{ "predicate": { "custom_model_data": 6421056 }, "model": "mechanization:machines/liquid_pipe/pipe_sew" },
		{ "predicate": { "custom_model_data": 6421057 }, "model": "mechanization:machines/liquid_pipe/pipe_usew" },
		{ "predicate": { "custom_model_data": 6421058 }, "model": "mechanization:machines/liquid_pipe/pipe_dsew" },
		{ "predicate": { "custom_model_data": 6421059 }, "model": "mechanization:machines/liquid_pipe/pipe_udsew" },
		{ "predicate": { "custom_model_data": 6421060 }, "model": "mechanization:machines/liquid_pipe/pipe_nsew" },
		{ "predicate": { "custom_model_data": 6421061 }, "model": "mechanization:machines/liquid_pipe/pipe_unsew" },
		{ "predicate": { "custom_model_data": 6421062 }, "model": "mechanization:machines/liquid_pipe/pipe_dnsew" },
		{ "predicate": { "custom_model_data": 6421063 }, "model": "mechanization:machines/liquid_pipe/pipe_udnsew" }
	]
}
